{
    "id": "39",
    "name": "Mathematical Disrespect",
    "author": "GDzoey",
    "creators": [],
    "verifier": "lucasestoes",
    "verification":   
"https://youtu.be/2kSWpLQmbvo",
    "password": "Locked with Password",
    "percentToQualify": 100,
    "difficulty": "Medium Demon",
    "pplacement": "3",
    "records": [
      {
            "user": "Niko",
            "link": "https://youtu.be/bcW7tuSfG1Q",
            "percent": 100,
            "hz": 120
        }, 
      {
            "user": "SFEXTI",
            "link": "https://youtu.be/ToxILKyTHt0?si=rpUgEbO3XVQUzwam",
            "percent": 100,
            "hz": 5758459
        }
    ]
}

    
